{"@context":"http://greendelta.github.io/olca-schema/context.jsonld","@type":"Flow","@id":"6cdca388-e12e-3661-a1e5-50cecc9a1dae","name":"Heat, waste","version":"00.00.000","category":{"@type":"Category","@id":"8ba39de4-085e-4d39-ac4c-6815df80d6fc","name":"unspecified"},"flowType":"ELEMENTARY_FLOW","infrastructureFlow":false,"flowProperties":[{"@type":"FlowPropertyFactor","referenceFlowProperty":true,"flowProperty":{"@type":"FlowProperty","@id":"f6811440-ee37-11de-8a39-0800200c9a66","name":"Energy"},"conversionFactor":1.0}]}