{"@context":"http://greendelta.github.io/olca-schema/context.jsonld","@type":"Flow","@id":"5ef7c19f-6cf9-35d2-827c-2f4e2780ce31","name":"Flame retardant, decaBDE","description":"CUTOFF flow","version":"00.00.003","category":{"@type":"Category","@id":"1a656790-0bd7-3fbc-b193-50dfbba1e8a0","name":"CUTOFF Flows","categoryPath":["Technosphere Flows"],"categoryType":"Flow"},"flowType":"PRODUCT_FLOW","cas":"NaN","formula":"NaN","infrastructureFlow":false,"flowProperties":[{"@type":"FlowPropertyFactor","referenceFlowProperty":true,"flowProperty":{"@type":"FlowProperty","@id":"93a60a56-a3c8-11da-a746-0800200b9a66","name":"Mass","categoryPath":["Technical flow properties"]},"conversionFactor":1.0}]}