{"@context":"http://greendelta.github.io/olca-schema/context.jsonld","@type":"Flow","@id":"ddd41ace-b67e-306c-908c-cdc7ee770808","name":"Water (river water from technosphere, turbined)","version":"00.00.000","category":{"@type":"Category","@id":"f862fd35-2379-456b-b51e-bb269e1bfe5b","name":"in water"},"flowType":"ELEMENTARY_FLOW","infrastructureFlow":false,"flowProperties":[{"@type":"FlowPropertyFactor","referenceFlowProperty":true,"flowProperty":{"@type":"FlowProperty","@id":"93a60a56-a3c8-11da-a746-0800200b9a66","name":"Mass"},"conversionFactor":1.0}]}