{"@context":"http://greendelta.github.io/olca-schema/context.jsonld","@type":"Process","@id":"45b70b50-20a0-341b-8e2f-c196974d1541","name":"Transport, single unit truck, diesel powered","description":"\nImportant note: although most of the data in the US LCI database has \nundergone some sort of review, the database as a whole has not yet \nundergone a formal validation process.\nPlease email comments to lci@nrel.gov.","version":"00.00.000","lastChange":"2013-10-22T14:14:50-06:00","category":{"@type":"Category","@id":"706e1c70-91b9-483d-bc87-7f898b157f03","name":"General Freight Trucking"},"processType":"UNIT_PROCESS","infrastructureProcess":false,"location":{"@type":"Location","@id":"b320e7db-c758-3ba6-8839-81eb83c9d7d7","name":"RNA"},"processDocumentation":{"@type":"ProcessDocumentation","technologyDescription":"Combustion of diesel in a single-unit truck.","restrictionsDescription":"All information can be accessed by everybody.","copyright":false,"validFrom":"2001-01-01T00:00:00-07:00","validUntil":"2001-01-01T00:00:00-07:00","creationDate":"2013-10-22T14:14:50-06:00","geographyDescription":"United States","dataDocumentor":{"@type":"Actor","@id":"b122816a-b081-373c-8564-44df6ffec96c","name":"Franklin Associates"},"dataGenerator":{"@type":"Actor","@id":"b122816a-b081-373c-8564-44df6ffec96c","name":"Franklin Associates"},"publication":{"@type":"Source","@id":"bf6d85fc-d40d-37a2-9d7b-cd2c2f473cc0","name":"Franklin Associates "},"sources":[{"@type":"Source","@id":"066f0b74-c38c-3bb4-acb8-a58bbf64f453","name":"unspecified "},{"@type":"Source","@id":"bf6d85fc-d40d-37a2-9d7b-cd2c2f473cc0","name":"Franklin Associates "},{"@type":"Source","@id":"9f5743aa-87b1-3ca9-82d9-d91f08537237","name":"Center for Transportation Reasearch, Arg "}]},"exchanges":[{"@type":"Exchange","avoidedProduct":false,"input":false,"amount":1.0,"flow":{"@type":"Flow","@id":"bbcd8095-e1d5-3762-aa08-3efc8d1d2ec4","name":"Transport, single unit truck, diesel powered","flowType":"PRODUCT_FLOW"},"unit":{"@type":"Unit","@id":"0dea4ed8-bb6b-4049-b2b4-b2c413ef2180","name":"t*km"},"flowProperty":{"@type":"FlowProperty","@id":"838aaa20-0117-11db-92e3-0800200c9a66","name":"Goods transport (mass*distance)"},"@id":"8ab478b9-e369-3f96-9843-627748647762","quantitativeReference":true},{"@type":"Exchange","avoidedProduct":false,"input":true,"amount":0.058338,"flow":{"@type":"Flow","@id":"d939590b-a0d7-310c-8952-9921ed64a078","name":"Diesel, at refinery","flowType":"PRODUCT_FLOW"},"unit":{"@type":"Unit","@id":"b80a512e-e402-4363-8ad0-7d02dcf4a459","name":"l"},"flowProperty":{"@type":"FlowProperty","@id":"93a60a56-a3c8-22da-a746-0800200c9a66","name":"Volume"},"@id":"869181b1-ba38-34bb-8046-d1f23194990b"},{"@type":"Exchange","avoidedProduct":false,"input":false,"amount":4.1257E-6,"flow":{"@type":"Flow","@id":"0795345f-c7ae-410c-ad25-1845784c75f5","name":"Methane, fossil","flowType":"ELEMENTARY_FLOW"},"unit":{"@type":"Unit","@id":"20aadc24-a391-41cf-b340-3e4529f44bde","name":"kg"},"flowProperty":{"@type":"FlowProperty","@id":"93a60a56-a3c8-11da-a746-0800200b9a66","name":"Mass"},"@id":"b63f3b15-e2c2-3eb9-bcbd-d4d6893be102"},{"@type":"Exchange","avoidedProduct":false,"input":false,"amount":3.7693E-5,"flow":{"@type":"Flow","@id":"e3569b8d-34ca-4712-93b5-b0d81f955663","name":"Sulfur oxides","flowType":"ELEMENTARY_FLOW"},"unit":{"@type":"Unit","@id":"20aadc24-a391-41cf-b340-3e4529f44bde","name":"kg"},"flowProperty":{"@type":"FlowProperty","@id":"93a60a56-a3c8-11da-a746-0800200b9a66","name":"Mass"},"@id":"080e737f-8ab3-34d2-8e62-5cd0a54fd70e"},{"@type":"Exchange","avoidedProduct":false,"input":false,"amount":0.17111,"flow":{"@type":"Flow","@id":"63af114b-afcb-3a82-801a-9c66208a673a","name":"Carbon dioxide, fossil ","flowType":"ELEMENTARY_FLOW"},"unit":{"@type":"Unit","@id":"20aadc24-a391-41cf-b340-3e4529f44bde","name":"kg"},"flowProperty":{"@type":"FlowProperty","@id":"93a60a56-a3c8-11da-a746-0800200b9a66","name":"Mass"},"@id":"aad5787c-cfb0-3b0b-b11a-d3a943530ef8"},{"@type":"Exchange","avoidedProduct":false,"input":false,"amount":0.0012188,"flow":{"@type":"Flow","@id":"c1b91234-6f24-417b-8309-46111d09c457","name":"Nitrogen oxides","flowType":"ELEMENTARY_FLOW"},"unit":{"@type":"Unit","@id":"20aadc24-a391-41cf-b340-3e4529f44bde","name":"kg"},"flowProperty":{"@type":"FlowProperty","@id":"93a60a56-a3c8-11da-a746-0800200b9a66","name":"Mass"},"@id":"480d3306-7955-3846-b856-00a80e66f1f8"},{"@type":"Exchange","avoidedProduct":false,"input":false,"amount":2.3537E-5,"flow":{"@type":"Flow","@id":"ae4dd6ba-67a2-3884-b7ce-2f5b38c0571a","name":"Particulates, \u003c 10 um ","flowType":"ELEMENTARY_FLOW"},"unit":{"@type":"Unit","@id":"20aadc24-a391-41cf-b340-3e4529f44bde","name":"kg"},"flowProperty":{"@type":"FlowProperty","@id":"93a60a56-a3c8-11da-a746-0800200b9a66","name":"Mass"},"@id":"68fe6968-389e-3758-96da-2dbade80699d"},{"@type":"Exchange","avoidedProduct":false,"input":false,"amount":8.4198E-5,"flow":{"@type":"Flow","@id":"7ae3bfc4-8532-11e0-9d78-0800200c9a66","name":"VOC, volatile organic compounds","flowType":"ELEMENTARY_FLOW"},"unit":{"@type":"Unit","@id":"20aadc24-a391-41cf-b340-3e4529f44bde","name":"kg"},"flowProperty":{"@type":"FlowProperty","@id":"93a60a56-a3c8-11da-a746-0800200b9a66","name":"Mass"},"@id":"349a8955-33fe-3676-98c6-b377e5cd231e"},{"@type":"Exchange","avoidedProduct":false,"input":false,"amount":2.4568E-4,"flow":{"@type":"Flow","@id":"8f6e6949-f569-3d05-abe1-de3608895d47","name":"Carbon monoxide, fossil ","flowType":"ELEMENTARY_FLOW"},"unit":{"@type":"Unit","@id":"20aadc24-a391-41cf-b340-3e4529f44bde","name":"kg"},"flowProperty":{"@type":"FlowProperty","@id":"93a60a56-a3c8-11da-a746-0800200b9a66","name":"Mass"},"@id":"3708f8e4-6752-3431-9460-95ff9223c9d1"},{"@type":"Exchange","avoidedProduct":false,"input":false,"amount":6.1875E-6,"flow":{"@type":"Flow","@id":"20185046-64bb-4c09-a8e7-e8a9e144ca98","name":"Dinitrogen monoxide","flowType":"ELEMENTARY_FLOW"},"unit":{"@type":"Unit","@id":"20aadc24-a391-41cf-b340-3e4529f44bde","name":"kg"},"flowProperty":{"@type":"FlowProperty","@id":"93a60a56-a3c8-11da-a746-0800200b9a66","name":"Mass"},"@id":"ec04c1fa-60f7-32de-b223-8b984eb1000b"}]}