{"@context":"http://greendelta.github.io/olca-schema/context.jsonld","@type":"Process","@id":"424444d2-67d5-3052-a42e-dde74b5dad37","name":"Trim and saw process, at plywood plant, US PNW","description":"Base process data presented with allocations to within process co-products noted.  Refer to allocation worksheet for specifics.  All allocations performed using mass or volume., number of co-products produced, some hogfuel remains in system\nImportant note: although most of the data in the US LCI database has \nundergone some sort of review, the database as a whole has not yet \nundergone a formal validation process.\nPlease email comments to lci@nrel.gov.","version":"00.00.000","lastChange":"2011-07-10T04:33:56-06:00","category":{"@type":"Category","@id":"ca565c38-869f-481d-bd46-ac35acdea72f","name":"Softwood Veneer and Plywood Manufacturing"},"processType":"UNIT_PROCESS","infrastructureProcess":false,"location":{"@type":"Location","@id":"b320e7db-c758-3ba6-8839-81eb83c9d7d7","name":"RNA"},"processDocumentation":{"@type":"ProcessDocumentation","technologyDescription":"typical","restrictionsDescription":"All information can be accessed by everybody.","copyright":true,"validFrom":"2000-01-01T00:00:00-07:00","validUntil":"2000-01-01T00:00:00-07:00","creationDate":"2011-07-10T04:33:56-06:00","geographyDescription":"US Pacific North West","dataDocumentor":{"@type":"Actor","@id":"0fd3778a-1e86-3dd2-a010-0d055620ef21","name":"Jamie Meil"},"dataGenerator":{"@type":"Actor","@id":"0fd3778a-1e86-3dd2-a010-0d055620ef21","name":"Jamie Meil"},"publication":{"@type":"Source","@id":"885ddfcd-9eab-3104-b315-ef6f088242f3","name":"Eric T. Sackimoto "},"sources":[{"@type":"Source","@id":"c802869a-677e-3a91-8e5d-a5774bcb76c4","name":"Leonard R. Johnson "},{"@type":"Source","@id":"885ddfcd-9eab-3104-b315-ef6f088242f3","name":"Eric T. Sackimoto "},{"@type":"Source","@id":"724b4aff-88d3-32c6-b791-067bad843f8a","name":"Maureen Puetmann "}]},"exchanges":[{"@type":"Exchange","avoidedProduct":false,"input":false,"amount":1.0,"flow":{"@type":"Flow","@id":"ea72f92a-274c-380d-834a-01752bd795e7","name":"Plywood, at plywood plant, US PNW","flowType":"PRODUCT_FLOW"},"unit":{"@type":"Unit","@id":"20aadc24-a391-41cf-b340-3e4529f44bde","name":"kg"},"flowProperty":{"@type":"FlowProperty","@id":"93a60a56-a3c8-11da-a746-0800200b9a66","name":"Mass"},"@id":"4cdd1a08-d0ee-364c-83b5-9cd563135678","quantitativeReference":true},{"@type":"Exchange","avoidedProduct":false,"input":false,"amount":1.07E-6,"flow":{"@type":"Flow","@id":"7ae398c3-8532-11e0-9d78-0800200c9a66","name":"Particulates, unspecified","flowType":"ELEMENTARY_FLOW"},"unit":{"@type":"Unit","@id":"20aadc24-a391-41cf-b340-3e4529f44bde","name":"kg"},"flowProperty":{"@type":"FlowProperty","@id":"93a60a56-a3c8-11da-a746-0800200b9a66","name":"Mass"},"@id":"ab5fd5c5-5de3-3700-b926-04ed2ba517d8"},{"@type":"Exchange","avoidedProduct":false,"input":true,"amount":0.0503,"flow":{"@type":"Flow","@id":"063de97f-fed9-351d-88bc-62062e4672fd","name":"Electricity, at grid, Western US, 2000","flowType":"PRODUCT_FLOW"},"unit":{"@type":"Unit","@id":"86ad2244-1f0e-4912-af53-7865283103e4","name":"kWh"},"flowProperty":{"@type":"FlowProperty","@id":"f6811440-ee37-11de-8a39-0800200c9a66","name":"Energy"},"@id":"b67159e8-cb42-3eee-8c20-f1fcb21d76e9"},{"@type":"Exchange","avoidedProduct":false,"input":false,"amount":0.114,"flow":{"@type":"Flow","@id":"9a0e33fd-0bb4-3e6b-9483-c4c57ea0d296","name":"Panel trim, from trim and saw at plywood plant, US PNW","flowType":"PRODUCT_FLOW"},"unit":{"@type":"Unit","@id":"20aadc24-a391-41cf-b340-3e4529f44bde","name":"kg"},"flowProperty":{"@type":"FlowProperty","@id":"93a60a56-a3c8-11da-a746-0800200b9a66","name":"Mass"},"@id":"591e0e68-637c-3fbe-8a74-a886cbc3c448"},{"@type":"Exchange","avoidedProduct":false,"input":true,"amount":1.27,"flow":{"@type":"Flow","@id":"6fc4d235-3e37-32ef-9326-d46ef4000cdf","name":"Pressed raw plywood, from lay-up, at plywood plant, US PNW","flowType":"PRODUCT_FLOW"},"unit":{"@type":"Unit","@id":"20aadc24-a391-41cf-b340-3e4529f44bde","name":"kg"},"flowProperty":{"@type":"FlowProperty","@id":"93a60a56-a3c8-11da-a746-0800200b9a66","name":"Mass"},"@id":"b73a907f-0420-3f0a-a957-f1e084e228b9"},{"@type":"Exchange","avoidedProduct":false,"input":true,"amount":4.9E-4,"flow":{"@type":"Flow","@id":"f77da622-e84d-3639-8917-fcf792aaee13","name":"Liquefied petroleum gas, combusted in industrial boiler","flowType":"PRODUCT_FLOW"},"unit":{"@type":"Unit","@id":"b80a512e-e402-4363-8ad0-7d02dcf4a459","name":"l"},"flowProperty":{"@type":"FlowProperty","@id":"93a60a56-a3c8-22da-a746-0800200c9a66","name":"Volume"},"@id":"8bc014f5-6857-3713-a3ce-4c2e77976792"},{"@type":"Exchange","avoidedProduct":false,"input":false,"amount":0.147,"flow":{"@type":"Flow","@id":"05547ccc-4429-3217-a3cc-22e944035288","name":"Hogfuel, from trim and saw at plywood plant, US PNW","flowType":"PRODUCT_FLOW"},"unit":{"@type":"Unit","@id":"20aadc24-a391-41cf-b340-3e4529f44bde","name":"kg"},"flowProperty":{"@type":"FlowProperty","@id":"93a60a56-a3c8-11da-a746-0800200b9a66","name":"Mass"},"@id":"955b91e1-4cfa-39e1-9b6c-f3a81c8cdc34"},{"@type":"Exchange","avoidedProduct":false,"input":false,"amount":0.0107,"flow":{"@type":"Flow","@id":"d829daf3-de93-3662-a299-9f57864afa12","name":"Sawdust, from trim and saw at plywood plant, US PNW","flowType":"PRODUCT_FLOW"},"unit":{"@type":"Unit","@id":"20aadc24-a391-41cf-b340-3e4529f44bde","name":"kg"},"flowProperty":{"@type":"FlowProperty","@id":"93a60a56-a3c8-11da-a746-0800200b9a66","name":"Mass"},"@id":"b68f8108-645d-3478-a1e3-6dbe2a626e78"}]}