{"@context":"http://greendelta.github.io/olca-schema/context.jsonld","@type":"Process","@id":"eaf32f1e-3780-3ccc-b6b0-1e0898524284","name":"Transport, school bus, diesel powered, East North Central","description":"This dataset represents the East North Central U.S. (IA, MI, MN, WI (Reference 10)) average airborne emissions for operating a diesel powered school bus. The inventory includes all vehicle operation processes, including off-network and refueling activities.\nThe refinery-to-pump transportation and distribution data are calculated from Argonne National Laboratory\u0027s GREET 1.8d.1 model.\nThe vehicle operation data are calculated from EPA\u0027s MOVES2010a model, using the assumptions described in the corresponding detailed spreadsheet.  Emissions factors in MOVES2010a are largely based on EPA\u0027s Mobile Source Observation Database, which in turn includes data from a variety of vehicle studies (References 6-8).\nMOVES2010a acknowledges sources of uncertainty in the model structure, the population and acitivty data, and other model parameters. As of July 2011, the uncertainty calculation function of the model has not been activated.","version":"00.00.000","lastChange":"2011-10-26T03:49:17-06:00","category":{"@type":"Category","@id":"4129a6ae-1985-4a7b-8b29-d095119454f7","name":"School and Employee Bus Transportation"},"processType":"UNIT_PROCESS","infrastructureProcess":false,"location":{"@type":"Location","@id":"b320e7db-c758-3ba6-8839-81eb83c9d7d7","name":"RNA"},"processDocumentation":{"@type":"ProcessDocumentation","technologyDescription":"Combustion of diesel in a school bus.","restrictionsDescription":"All information can be accessed by everybody.","copyright":false,"validFrom":"2010-01-01T00:00:00-07:00","validUntil":"2010-01-01T00:00:00-07:00","creationDate":"2011-10-26T03:49:17-06:00","geographyDescription":"US","dataDocumentor":{"@type":"Actor","@id":"46308ae8-5bc9-3e99-9f16-03367fa3ea27","name":"Nathan Hardesty"},"dataGenerator":{"@type":"Actor","@id":"46308ae8-5bc9-3e99-9f16-03367fa3ea27","name":"Nathan Hardesty"},"publication":{"@type":"Source","@id":"4bd80a48-814e-328c-a963-91d1edd74378","name":"U.S. Environmental Protection Agency (EP "},"sources":[{"@type":"Source","@id":"4bd80a48-814e-328c-a963-91d1edd74378","name":"U.S. Environmental Protection Agency (EP "},{"@type":"Source","@id":"55c36137-f07a-367a-a6b5-46062d46120b","name":"National Institute of Standards and Tech "},{"@type":"Source","@id":"42c7ed98-38f6-3ed7-b347-bc2d66b3ee74","name":"EPA "},{"@type":"Source","@id":"7ef58755-a0b6-3a5d-9dc0-5a7d5c2b7479","name":"U.S. Alternative Fuels and Advanced Vehi "},{"@type":"Source","@id":"5e145cd8-7bb1-3a05-b869-99934f6860a3","name":"Eastern Research Group "},{"@type":"Source","@id":"1579e4fb-7f2f-3cba-a12d-9140aa520c8f","name":"Assessment and Standards Division, Offic "},{"@type":"Source","@id":"9b5ffc93-55dd-3784-b5b2-a5996a73b6ac","name":"Assessment and Standards Division, Offic "},{"@type":"Source","@id":"6b8aab96-3e01-34ad-8e70-be6dd4f71977","name":"Wang, M. "},{"@type":"Source","@id":"b5ce2760-ed4f-3cfe-8df6-43efce7b5acc","name":"National Climatic Data Center, National  "},{"@type":"Source","@id":"a752c39b-4372-39e2-ab1a-2ff252f1ee4f","name":"American School Bus Council "}]},"exchanges":[{"@type":"Exchange","avoidedProduct":false,"input":false,"amount":1.0,"flow":{"@type":"Flow","@id":"19cb2855-b05f-34e2-9790-f00eff4d4094","name":"Transport, school bus, diesel powered, East North Central","flowType":"PRODUCT_FLOW"},"unit":{"@type":"Unit","@id":"fe8da65d-f0ea-4496-b13e-1955aaa412d7","name":"p*km"},"flowProperty":{"@type":"FlowProperty","@id":"8766e10f-9f41-4db0-8173-ad0d002a5b98","name":"Person transport"},"@id":"d205eafc-db5a-33b4-9f6f-0541e1943951","quantitativeReference":true},{"@type":"Exchange","avoidedProduct":false,"input":true,"amount":0.0025073434300282,"flow":{"@type":"Flow","@id":"73c7494d-4e93-3769-896b-8bb82f0dfccc","name":"Transport, train, diesel powered","flowType":"PRODUCT_FLOW"},"unit":{"@type":"Unit","@id":"0dea4ed8-bb6b-4049-b2b4-b2c413ef2180","name":"t*km"},"flowProperty":{"@type":"FlowProperty","@id":"838aaa20-0117-11db-92e3-0800200c9a66","name":"Goods transport (mass*distance)"},"@id":"374cd7b2-d616-350a-9a84-babfd44556f7"},{"@type":"Exchange","avoidedProduct":false,"input":false,"amount":0.0109432154298866,"flow":{"@type":"Flow","@id":"63af114b-afcb-3a82-801a-9c66208a673a","name":"Carbon dioxide, fossil ","flowType":"ELEMENTARY_FLOW"},"unit":{"@type":"Unit","@id":"20aadc24-a391-41cf-b340-3e4529f44bde","name":"kg"},"flowProperty":{"@type":"FlowProperty","@id":"93a60a56-a3c8-11da-a746-0800200b9a66","name":"Mass"},"@id":"87c97d03-5eb1-3314-8e9f-5f39acf52705"},{"@type":"Exchange","avoidedProduct":false,"input":false,"amount":8.78713136816044E-5,"flow":{"@type":"Flow","@id":"e8244140-0551-38e9-8143-4bb8be8488e9","name":"Nitrogen oxide ","flowType":"ELEMENTARY_FLOW"},"unit":{"@type":"Unit","@id":"20aadc24-a391-41cf-b340-3e4529f44bde","name":"kg"},"flowProperty":{"@type":"FlowProperty","@id":"93a60a56-a3c8-11da-a746-0800200b9a66","name":"Mass"},"@id":"6f916758-cb75-3952-9dd0-1545a8844c6f"},{"@type":"Exchange","avoidedProduct":false,"input":false,"amount":5.01818412598689E-6,"description":"PM10 from organic carbon, elemental carbon, and sulfate particulates.","flow":{"@type":"Flow","@id":"ae4dd6ba-67a2-3884-b7ce-2f5b38c0571a","name":"Particulates, \u003c 10 um ","flowType":"ELEMENTARY_FLOW"},"unit":{"@type":"Unit","@id":"20aadc24-a391-41cf-b340-3e4529f44bde","name":"kg"},"flowProperty":{"@type":"FlowProperty","@id":"93a60a56-a3c8-11da-a746-0800200b9a66","name":"Mass"},"@id":"2e16c310-a141-36ac-bd1e-3b8139bb1218"},{"@type":"Exchange","avoidedProduct":false,"input":true,"amount":0.00416807165644896,"flow":{"@type":"Flow","@id":"d939590b-a0d7-310c-8952-9921ed64a078","name":"Diesel, at refinery","flowType":"PRODUCT_FLOW"},"unit":{"@type":"Unit","@id":"b80a512e-e402-4363-8ad0-7d02dcf4a459","name":"l"},"flowProperty":{"@type":"FlowProperty","@id":"93a60a56-a3c8-22da-a746-0800200c9a66","name":"Volume"},"@id":"9b1d5dcb-a399-3893-b089-f4b90ad737d6"},{"@type":"Exchange","avoidedProduct":false,"input":false,"amount":1.91485726100919E-7,"description":"PM10 from tirewear.","flow":{"@type":"Flow","@id":"ae4dd6ba-67a2-3884-b7ce-2f5b38c0571a","name":"Particulates, \u003c 10 um ","flowType":"ELEMENTARY_FLOW"},"unit":{"@type":"Unit","@id":"20aadc24-a391-41cf-b340-3e4529f44bde","name":"kg"},"flowProperty":{"@type":"FlowProperty","@id":"93a60a56-a3c8-11da-a746-0800200b9a66","name":"Mass"},"@id":"af61663d-d924-3cd2-8dc5-2c29c776aac6"},{"@type":"Exchange","avoidedProduct":false,"input":false,"amount":9.57538827787869E-5,"flow":{"@type":"Flow","@id":"c1b91234-6f24-417b-8309-46111d09c457","name":"Nitrogen oxides","flowType":"ELEMENTARY_FLOW"},"unit":{"@type":"Unit","@id":"20aadc24-a391-41cf-b340-3e4529f44bde","name":"kg"},"flowProperty":{"@type":"FlowProperty","@id":"93a60a56-a3c8-11da-a746-0800200b9a66","name":"Mass"},"@id":"dfee8633-3a17-3268-bc8f-94225fc52e9e"},{"@type":"Exchange","avoidedProduct":false,"input":false,"amount":9.44564334590797E-6,"flow":{"@type":"Flow","@id":"7ae3bfc4-8532-11e0-9d78-0800200c9a66","name":"VOC, volatile organic compounds","flowType":"ELEMENTARY_FLOW"},"unit":{"@type":"Unit","@id":"20aadc24-a391-41cf-b340-3e4529f44bde","name":"kg"},"flowProperty":{"@type":"FlowProperty","@id":"93a60a56-a3c8-11da-a746-0800200b9a66","name":"Mass"},"@id":"220d832b-ab92-3a67-891c-2251ff36b83d"},{"@type":"Exchange","avoidedProduct":false,"input":false,"amount":7.88276700250751E-6,"flow":{"@type":"Flow","@id":"0b7e10a8-6ca0-4a50-a39b-f2a019cb3610","name":"Nitrogen dioxide","flowType":"ELEMENTARY_FLOW"},"unit":{"@type":"Unit","@id":"20aadc24-a391-41cf-b340-3e4529f44bde","name":"kg"},"flowProperty":{"@type":"FlowProperty","@id":"93a60a56-a3c8-11da-a746-0800200b9a66","name":"Mass"},"@id":"77924bca-4d7a-3e14-b89b-9c4107bdd9a6"},{"@type":"Exchange","avoidedProduct":false,"input":true,"amount":0.00918546942893241,"flow":{"@type":"Flow","@id":"0e63d1db-e383-3c9a-b02a-b5eebafe87d1","name":"Transport, ocean freighter, average fuel mix","flowType":"PRODUCT_FLOW"},"unit":{"@type":"Unit","@id":"0dea4ed8-bb6b-4049-b2b4-b2c413ef2180","name":"t*km"},"flowProperty":{"@type":"FlowProperty","@id":"838aaa20-0117-11db-92e3-0800200c9a66","name":"Goods transport (mass*distance)"},"@id":"289bd300-16f6-3595-8dcb-73c325289311"},{"@type":"Exchange","avoidedProduct":false,"input":true,"amount":0.0135431350501361,"flow":{"@type":"Flow","@id":"acbe5bc4-6afd-31aa-bf3f-4a3fdc491945","name":"Transport, pipeline, unspecified petroleum products","flowType":"PRODUCT_FLOW"},"unit":{"@type":"Unit","@id":"0dea4ed8-bb6b-4049-b2b4-b2c413ef2180","name":"t*km"},"flowProperty":{"@type":"FlowProperty","@id":"838aaa20-0117-11db-92e3-0800200c9a66","name":"Goods transport (mass*distance)"},"@id":"aba3e2c1-3c47-36ef-a10b-26b88766a91d"},{"@type":"Exchange","avoidedProduct":false,"input":false,"amount":1.8484357360704E-7,"flow":{"@type":"Flow","@id":"fd7aa71c-508c-480d-81a6-8052aad92646","name":"Sulfur dioxide","flowType":"ELEMENTARY_FLOW"},"unit":{"@type":"Unit","@id":"20aadc24-a391-41cf-b340-3e4529f44bde","name":"kg"},"flowProperty":{"@type":"FlowProperty","@id":"93a60a56-a3c8-11da-a746-0800200b9a66","name":"Mass"},"@id":"8c077f71-3ae3-35d7-b863-bfb559696544"},{"@type":"Exchange","avoidedProduct":false,"input":false,"amount":9.15289639165968E-6,"flow":{"@type":"Flow","@id":"5923640b-eb9e-3728-a0e0-70453c1bf425","name":"Hydrocarbons (other than methane)","flowType":"ELEMENTARY_FLOW"},"unit":{"@type":"Unit","@id":"20aadc24-a391-41cf-b340-3e4529f44bde","name":"kg"},"flowProperty":{"@type":"FlowProperty","@id":"93a60a56-a3c8-11da-a746-0800200b9a66","name":"Mass"},"@id":"bbd1f11f-54e4-3b79-9a3a-3c660fe84945"},{"@type":"Exchange","avoidedProduct":false,"input":true,"amount":0.00129958547028757,"flow":{"@type":"Flow","@id":"4069483a-8d94-3b6b-81be-5f0a249b74f4","name":"Transport, barge, average fuel mix","flowType":"PRODUCT_FLOW"},"unit":{"@type":"Unit","@id":"0dea4ed8-bb6b-4049-b2b4-b2c413ef2180","name":"t*km"},"flowProperty":{"@type":"FlowProperty","@id":"838aaa20-0117-11db-92e3-0800200c9a66","name":"Goods transport (mass*distance)"},"@id":"775428b3-0f01-3d30-8235-e96cc3a65515"},{"@type":"Exchange","avoidedProduct":false,"input":false,"amount":4.59198466341679E-8,"description":"PM2.5 from tirewear.","flow":{"@type":"Flow","@id":"21e46cb8-6233-4c99-bac3-c41d2ab99498","name":"Particulates, \u003c 2.5 um","flowType":"ELEMENTARY_FLOW"},"unit":{"@type":"Unit","@id":"20aadc24-a391-41cf-b340-3e4529f44bde","name":"kg"},"flowProperty":{"@type":"FlowProperty","@id":"93a60a56-a3c8-11da-a746-0800200b9a66","name":"Mass"},"@id":"715f87ca-80d5-3fab-b2bd-b0dc64f0e46d"},{"@type":"Exchange","avoidedProduct":false,"input":false,"amount":1.82892631908285E-7,"description":" PM2.5 from brakewear.","flow":{"@type":"Flow","@id":"21e46cb8-6233-4c99-bac3-c41d2ab99498","name":"Particulates, \u003c 2.5 um","flowType":"ELEMENTARY_FLOW"},"unit":{"@type":"Unit","@id":"20aadc24-a391-41cf-b340-3e4529f44bde","name":"kg"},"flowProperty":{"@type":"FlowProperty","@id":"93a60a56-a3c8-11da-a746-0800200b9a66","name":"Mass"},"@id":"d86b0e39-a589-346b-9f1e-b86b7dce0bd7"},{"@type":"Exchange","avoidedProduct":false,"input":false,"amount":4.86782240677793E-6,"description":" PM2.5 from organic carbon, elemental carbon, and sulfate particulates.","flow":{"@type":"Flow","@id":"21e46cb8-6233-4c99-bac3-c41d2ab99498","name":"Particulates, \u003c 2.5 um","flowType":"ELEMENTARY_FLOW"},"unit":{"@type":"Unit","@id":"20aadc24-a391-41cf-b340-3e4529f44bde","name":"kg"},"flowProperty":{"@type":"FlowProperty","@id":"93a60a56-a3c8-11da-a746-0800200b9a66","name":"Mass"},"@id":"65835cd3-2ead-3174-a285-25d5469f9adf"},{"@type":"Exchange","avoidedProduct":false,"input":true,"amount":0.00134361097185335,"flow":{"@type":"Flow","@id":"2afb4e2f-b224-3900-956f-03e3f27b276b","name":"Transport, combination truck, average fuel mix","flowType":"PRODUCT_FLOW"},"unit":{"@type":"Unit","@id":"0dea4ed8-bb6b-4049-b2b4-b2c413ef2180","name":"t*km"},"flowProperty":{"@type":"FlowProperty","@id":"838aaa20-0117-11db-92e3-0800200c9a66","name":"Goods transport (mass*distance)"},"@id":"b0fdd99d-34f9-3581-85ff-0e6164f905e8"},{"@type":"Exchange","avoidedProduct":false,"input":false,"amount":6.98649966335854E-7,"description":"PM10 from brakewear.","flow":{"@type":"Flow","@id":"ae4dd6ba-67a2-3884-b7ce-2f5b38c0571a","name":"Particulates, \u003c 10 um ","flowType":"ELEMENTARY_FLOW"},"unit":{"@type":"Unit","@id":"20aadc24-a391-41cf-b340-3e4529f44bde","name":"kg"},"flowProperty":{"@type":"FlowProperty","@id":"93a60a56-a3c8-11da-a746-0800200b9a66","name":"Mass"},"@id":"187243f7-a713-3664-a5cc-c7a83f6fa8b5"},{"@type":"Exchange","avoidedProduct":false,"input":false,"amount":2.14551681693753E-7,"flow":{"@type":"Flow","@id":"87883a4e-1e3e-4c9d-90c0-f1bea36f8014","name":"Ammonia","flowType":"ELEMENTARY_FLOW"},"unit":{"@type":"Unit","@id":"20aadc24-a391-41cf-b340-3e4529f44bde","name":"kg"},"flowProperty":{"@type":"FlowProperty","@id":"93a60a56-a3c8-11da-a746-0800200b9a66","name":"Mass"},"@id":"9e08f1b6-4e80-369e-80e7-9956214f589d"},{"@type":"Exchange","avoidedProduct":false,"input":false,"amount":6.01668440842927E-5,"flow":{"@type":"Flow","@id":"8f6e6949-f569-3d05-abe1-de3608895d47","name":"Carbon monoxide, fossil ","flowType":"ELEMENTARY_FLOW"},"unit":{"@type":"Unit","@id":"20aadc24-a391-41cf-b340-3e4529f44bde","name":"kg"},"flowProperty":{"@type":"FlowProperty","@id":"93a60a56-a3c8-11da-a746-0800200b9a66","name":"Mass"},"@id":"133aee67-6d1f-3a76-b612-e46c14569a34"},{"@type":"Exchange","avoidedProduct":false,"input":false,"amount":5.04041968882716E-8,"flow":{"@type":"Flow","@id":"20185046-64bb-4c09-a8e7-e8a9e144ca98","name":"Dinitrogen monoxide","flowType":"ELEMENTARY_FLOW"},"unit":{"@type":"Unit","@id":"20aadc24-a391-41cf-b340-3e4529f44bde","name":"kg"},"flowProperty":{"@type":"FlowProperty","@id":"93a60a56-a3c8-11da-a746-0800200b9a66","name":"Mass"},"@id":"41959386-9387-3c73-bca4-359d9df09868"},{"@type":"Exchange","avoidedProduct":false,"input":false,"amount":6.01502650154706E-7,"flow":{"@type":"Flow","@id":"20408dd1-8534-11e0-9d78-0800200c9a66","name":"Methane","flowType":"ELEMENTARY_FLOW"},"unit":{"@type":"Unit","@id":"20aadc24-a391-41cf-b340-3e4529f44bde","name":"kg"},"flowProperty":{"@type":"FlowProperty","@id":"93a60a56-a3c8-11da-a746-0800200b9a66","name":"Mass"},"@id":"655c6a4e-b57c-3c14-98a2-56457d2bb4e8"}]}